{
	"info": {
		"_postman_id": "5c7adb17-74d8-4026-87a0-b76124c70d6b",
		"name": "Golang_HealthCare_BharatSeva",
		"schema": "https://schema.getpostman.com/json/collection/v2.0.0/collection.json",
		"_exporter_id": "24259607"
	},
	"item": [
		{
			"name": "Register",
			"event": [
				{
					"listen": "test",
					"script": {
						"exec": [
							"var jsonData = pm.response.json();\r",
							"var healthcare_id = jsonData.Healthcare_details.healthcare_id;\r",
							"\r",
							"pm.collectionVariables.set(\"H_ID\", healthcare_id);"
						],
						"type": "text/javascript",
						"packages": {}
					}
				}
			],
			"request": {
				"method": "POST",
				"header": [],
				"body": {
					"mode": "raw",
					"raw": "{\r\n    \"name\": \"{{$randomFullName}} Hospital\",\r\n    \"availability\": \"Yes\",\r\n    \"total_facilities\": 200,\r\n    \"total_mbbs_doc\": 58,\r\n    \"total_worker\": 400,\r\n    \"no_of_beds\": 200,\r\n    \"email\": \"{{$randomEmail}}\",\r\n    \"appointment_fee\": 300,\r\n    \"about\": \"{{$randomJobDescriptor}}\",\r\n    \"password\": \"11\",\r\n    \"address\": {\r\n        \"country\": \"{{$randomCountry}}\",\r\n        \"landmark\": \"{{$randomStreetName}}\",\r\n        \"city\": \"{{$randomCity}}\",\r\n        \"state\": \"{{$randomCity}}\"\r\n    }\r\n}",
					"options": {
						"raw": {
							"language": "json"
						}
					}
				},
				"url": "http://localhost/api/v1/healthcare/auth/register"
			},
			"response": [
				{
					"name": "Register",
					"originalRequest": {
						"method": "POST",
						"header": [],
						"body": {
							"mode": "raw",
							"raw": "{\r\n    \"name\": \"{{$randomFullName}} Hospital\",\r\n    \"availability\": \"Yes\",\r\n    \"total_facilities\": 200,\r\n    \"total_mbbs_doc\": 58,\r\n    \"total_worker\": 400,\r\n    \"no_of_beds\": 200,\r\n    \"email\": \"{{$randomEmail}}\",\r\n    \"appointment_fee\": 300,\r\n    \"about\": \"{{$randomJobDescriptor}}\",\r\n    \"password\": \"11\",\r\n    \"address\": {\r\n        \"country\": \"{{$randomCountry}}\",\r\n        \"landmark\": \"{{$randomStreetName}}\",\r\n        \"city\": \"{{$randomCity}}\",\r\n        \"state\": \"{{$randomCity}}\"\r\n    }\r\n}",
							"options": {
								"raw": {
									"language": "json"
								}
							}
						},
						"url": "http://localhost:3000/api/v1/healthcareauth/register"
					},
					"status": "Created",
					"code": 201,
					"_postman_previewlanguage": "json",
					"header": [
						{
							"key": "Content-Type",
							"value": "application/json"
						},
						{
							"key": "Date",
							"value": "Sat, 26 Oct 2024 14:41:18 GMT"
						},
						{
							"key": "Content-Length",
							"value": "217"
						}
					],
					"cookie": [],
					"body": "{\n    \"Healthcare_details\": {\n        \"email\": \"Camylle.Reichel@yahoo.com\",\n        \"healthcare_id\": \"HCID04bd4df0-060d-43d1-a\",\n        \"healthcare_license\": \"04bd4df0-060d-43d1-a\",\n        \"name\": \"Christina Medhurst Hospital\"\n    },\n    \"status\": \"Successfully Created\"\n}"
				}
			]
		},
		{
			"name": "Login",
			"event": [
				{
					"listen": "test",
					"script": {
						"exec": [
							"var jsonData = pm.response.json();\r",
							"\r",
							"var token = jsonData.token;\r",
							"pm.collectionVariables.set(\"HIP_TOKEN\", token);\r",
							"\r",
							"var healthcare_id = jsonData.healthcare_id;\r",
							"pm.globals.set(\"healthcare_id\", healthcare_id)\r",
							"\r",
							"var healthcare_name = jsonData.healthcare_name\r",
							"pm.globals.set(\"healthcare_name\", healthcare_name)"
						],
						"type": "text/javascript",
						"packages": {}
					}
				},
				{
					"listen": "prerequest",
					"script": {
						"exec": [
							""
						],
						"type": "text/javascript",
						"packages": {}
					}
				}
			],
			"request": {
				"method": "POST",
				"header": [],
				"body": {
					"mode": "raw",
					"raw": "{\r\n    \"healthcare_id\": \"{{H_ID}}\",\r\n    \"healthcare_license\": \"{{H_ID}}\",\r\n    \"password\": \"11\"\r\n}",
					"options": {
						"raw": {
							"language": "json"
						}
					}
				},
				"url": "http://localhost/api/v1/healthcare/auth/login"
			},
			"response": [
				{
					"name": "Login",
					"originalRequest": {
						"method": "POST",
						"header": [],
						"body": {
							"mode": "raw",
							"raw": "{\r\n    \"healthcare_id\": \"{{H_ID}}\",\r\n    \"healthcare_license\": \"{{H_ID}}\",\r\n    \"password\": \"11\"\r\n}",
							"options": {
								"raw": {
									"language": "json"
								}
							}
						},
						"url": "http://localhost:3000/api/v1/healthcareauth/login"
					},
					"status": "OK",
					"code": 200,
					"_postman_previewlanguage": "json",
					"header": [
						{
							"key": "Content-Type",
							"value": "application/json"
						},
						{
							"key": "Date",
							"value": "Sat, 26 Oct 2024 14:41:35 GMT"
						},
						{
							"key": "Content-Length",
							"value": "291"
						}
					],
					"cookie": [],
					"body": "{\n    \"Expires In\": \"5d\",\n    \"healthcare_id\": \"HCID04bd4df0-060d-43d1-a\",\n    \"healthcare_name\": \"Christina Medhurst Hospital\",\n    \"token\": \"eyJhbGciOiJIUzI1NiIsInR5cCI6IkpXVCJ9.eyJleHBpcmVzQXQiOjE3MzAzODU2OTUsImhlYWx0aGNhcmVJRCI6IkhDSUQwNGJkNGRmMC0wNjBkLTQzZDEtYSJ9.tH_J6FZ39Iz-ExHJrSB8im3OxpLvz-sufzfXXDiSFl4\"\n}"
				}
			]
		},
		{
			"name": "Change Preferance",
			"request": {
				"auth": {
					"type": "bearer",
					"bearer": {
						"token": "{{HIP_TOKEN}}"
					}
				},
				"method": "PATCH",
				"header": [],
				"body": {
					"mode": "raw",
					"raw": "{\r\n    \"email\": \"{{$randomEmail}}\",\r\n    \"isAvailable\": true,\r\n    \"scheduled_deletion\": false\r\n}",
					"options": {
						"raw": {
							"language": "json"
						}
					}
				},
				"url": "http://localhost/api/v1/healthcare/changepreferance"
			},
			"response": [
				{
					"name": "Change Preferance",
					"originalRequest": {
						"method": "PATCH",
						"header": [],
						"body": {
							"mode": "raw",
							"raw": "{\r\n    \"email\": \"{{$randomEmail}}\",\r\n    \"isAvailable\": true,\r\n    \"scheduled_deletion\": false\r\n}",
							"options": {
								"raw": {
									"language": "json"
								}
							}
						},
						"url": "http://localhost:3000/api/v1/healthcare/changepreferance"
					},
					"status": "OK",
					"code": 200,
					"_postman_previewlanguage": "json",
					"header": [
						{
							"key": "Content-Type",
							"value": "application/json"
						},
						{
							"key": "Date",
							"value": "Sat, 26 Oct 2024 14:41:47 GMT"
						},
						{
							"key": "Content-Length",
							"value": "88"
						}
					],
					"cookie": [],
					"body": "{\n    \"email\": \"Roselyn.Marquardt79@yahoo.com\",\n    \"isAvailable\": true,\n    \"scheduled_deletion\": false\n}"
				}
			]
		},
		{
			"name": "Get Preferance",
			"request": {
				"auth": {
					"type": "bearer",
					"bearer": {
						"token": "{{HIP_TOKEN}}"
					}
				},
				"method": "GET",
				"header": [],
				"url": {
					"raw": "http://localhost/api/v1/healthcare/getpreferance?cache=false",
					"protocol": "http",
					"host": [
						"localhost"
					],
					"path": [
						"api",
						"v1",
						"healthcare",
						"getpreferance"
					],
					"query": [
						{
							"key": "cache",
							"value": "false"
						}
					]
				}
			},
			"response": [
				{
					"name": "Get Preferance (without cache)",
					"originalRequest": {
						"method": "GET",
						"header": [],
						"url": "http://localhost:3000/api/v1/healthcare/getpreferance"
					},
					"status": "OK",
					"code": 200,
					"_postman_previewlanguage": "json",
					"header": [
						{
							"key": "Content-Type",
							"value": "application/json"
						},
						{
							"key": "Date",
							"value": "Sat, 26 Oct 2024 05:41:19 GMT"
						},
						{
							"key": "Content-Length",
							"value": "117"
						}
					],
					"cookie": [],
					"body": "{\n    \"preferance\": {\n        \"email\": \"Santa_Rath72@gmail.com\",\n        \"isAvailable\": true,\n        \"scheduled_deletion\": true\n    }\n}"
				},
				{
					"name": "Get Preferance (with cache)",
					"originalRequest": {
						"method": "GET",
						"header": [],
						"url": {
							"raw": "http://localhost:3000/api/v1/healthcare/getpreferance?cache=true",
							"protocol": "http",
							"host": [
								"localhost"
							],
							"port": "3000",
							"path": [
								"api",
								"v1",
								"healthcare",
								"getpreferance"
							],
							"query": [
								{
									"key": "cache",
									"value": "true"
								}
							]
						}
					},
					"status": "OK",
					"code": 200,
					"_postman_previewlanguage": "json",
					"header": [
						{
							"key": "Content-Type",
							"value": "application/json"
						},
						{
							"key": "Date",
							"value": "Sat, 26 Oct 2024 05:46:39 GMT"
						},
						{
							"key": "Content-Length",
							"value": "95"
						}
					],
					"cookie": [],
					"body": "{\n    \"preferance\": {\n        \"email\": \"Santa_Rath72@gmail.com\",\n        \"isAvailable\": true,\n        \"scheduled_deletion\": true\n    }\n}"
				}
			]
		},
		{
			"name": "Get Appointments",
			"event": [
				{
					"listen": "test",
					"script": {
						"exec": [
							"var jsonData = pm.response.json();\r",
							"var appointmentlength = jsonData.appointments.length\r",
							"const randomNumber = Math.floor(Math.random() * appointmentlength);\r",
							"\r",
							"var appointment_id = jsonData.appointments[randomNumber].id\r",
							"pm.collectionVariables.set(\"app_id\", appointment_id);\r",
							""
						],
						"type": "text/javascript",
						"packages": {}
					}
				}
			],
			"request": {
				"auth": {
					"type": "bearer",
					"bearer": {
						"token": "{{HIP_TOKEN}}"
					}
				},
				"method": "GET",
				"header": [],
				"url": {
					"raw": "http://localhost/api/v1/healthcare/appointments/get?list=10",
					"protocol": "http",
					"host": [
						"localhost"
					],
					"path": [
						"api",
						"v1",
						"healthcare",
						"appointments",
						"get"
					],
					"query": [
						{
							"key": "list",
							"value": "10"
						}
					]
				}
			},
			"response": [
				{
					"name": "Get Appointments",
					"originalRequest": {
						"method": "GET",
						"header": [],
						"url": {
							"raw": "http://localhost:3000/api/v1/healthcare/getappointments?list=2",
							"protocol": "http",
							"host": [
								"localhost"
							],
							"port": "3000",
							"path": [
								"api",
								"v1",
								"healthcare",
								"getappointments"
							],
							"query": [
								{
									"key": "list",
									"value": "2"
								}
							]
						}
					},
					"status": "OK",
					"code": 200,
					"_postman_previewlanguage": "json",
					"header": [
						{
							"key": "Content-Type",
							"value": "application/json"
						},
						{
							"key": "Date",
							"value": "Sat, 26 Oct 2024 14:41:58 GMT"
						},
						{
							"key": "Content-Length",
							"value": "37"
						}
					],
					"cookie": [],
					"body": "{\n    \"appointments\": null,\n    \"pagination\": 2\n}"
				}
			]
		},
		{
			"name": "Delete Account",
			"request": {
				"auth": {
					"type": "bearer",
					"bearer": {
						"token": "{{HIP_TOKEN}}"
					}
				},
				"method": "DELETE",
				"header": [],
				"url": "http://localhost:3000/api/v1/healthcare/deleteaccount"
			},
			"response": [
				{
					"name": "Delete Account",
					"originalRequest": {
						"method": "DELETE",
						"header": [],
						"url": "http://localhost:3000/api/v1/healthcare/deleteaccount"
					},
					"status": "OK",
					"code": 200,
					"_postman_previewlanguage": "json",
					"header": [
						{
							"key": "Content-Type",
							"value": "application/json"
						},
						{
							"key": "Date",
							"value": "Sat, 26 Oct 2024 14:42:06 GMT"
						},
						{
							"key": "Content-Length",
							"value": "101"
						}
					],
					"cookie": [],
					"body": "{\n    \"status\": \"account deletion scheduled, contact to tron21vaibhav@gmail.com to remove deletion ASAP.\"\n}"
				}
			]
		},
		{
			"name": "Create Patient Bio-data",
			"event": [
				{
					"listen": "test",
					"script": {
						"exec": [
							"var jsonData = pm.response.json();\r",
							"\r",
							"var patient_healthID = jsonData.patient_healthID;\r",
							"pm.globals.set(\"health_id\", patient_healthID);\r",
							"\r",
							"\r",
							"var patient_email = jsonData.email;\r",
							"pm.globals.set(\"patient_email\", patient_email)\r",
							""
						],
						"type": "text/javascript",
						"packages": {}
					}
				}
			],
			"request": {
				"auth": {
					"type": "bearer",
					"bearer": {
						"token": "{{HIP_TOKEN}}"
					}
				},
				"method": "POST",
				"header": [],
				"body": {
					"mode": "raw",
					"raw": "{\r\n    \"fname\": \"{{$randomFullName}}\",\r\n    \"middlename\": \"Kumar\",\r\n    \"lname\": \"{{$randomLastName}}\",\r\n    \"sex\": \"Male\",\r\n    \"dob\": \"{{$randomDateRecent}}\",\r\n    \"bloodgrp\": \"{{$randomAlphaNumeric}}\",\r\n    \"bmi\": \"{{$randomAlphaNumeric}}\",\r\n    \"marriage_status\": \"Single\",\r\n    \"weight\": \"{{$randomPhoneNumberExt}}\",\r\n    \"email\": \"{{$randomEmail}}\",\r\n    \"mobilenumber\": \"{{$randomPhoneNumber}}\",\r\n    \"aadhar_number\": \"{{$randomPhoneNumber}}\",\r\n    \"primary_location\": \"{{$randomLocale}}\",\r\n    \"sibling\": \"{{$randomBoolean}}\",\r\n    \"twin\": \"{{$randomBoolean}}\",\r\n    \"fathername\": \"{{$randomFullName}}\",\r\n    \"mothername\": \"{{$randomUserName}}\",\r\n    \"emergencynumber\": \"{{$randomPhoneNumber}}\",\r\n    \"address\": {\r\n        \"country\": \"{{$randomCountry}}\",\r\n        \"state\": \"{{$randomStreetName}}\",\r\n        \"city\": \"{{$randomCity}}\",\r\n        \"landmark\": \"{{$randomStreetAddress}}\"\r\n    }\r\n}",
					"options": {
						"raw": {
							"language": "json"
						}
					}
				},
				"url": "http://localhost/api/v1/healthcare/createpatientbiodata"
			},
			"response": [
				{
					"name": "Create Patient Bio-data",
					"originalRequest": {
						"method": "POST",
						"header": [],
						"body": {
							"mode": "raw",
							"raw": "{\r\n    \"fname\": \"{{$randomFullName}}\",\r\n    \"middlename\": \"Kumar\",\r\n    \"lname\": \"{{$randomLastName}}\",\r\n    \"sex\": \"Male\",\r\n    \"dob\": \"DOMD\",\r\n    \"bloodgrp\": \"N/A\",\r\n    \"bmi\": \"N/A\",\r\n    \"marriage_status\": \"Single\",\r\n    \"weight\": \"N/A\",\r\n    \"email\": \"{{$randomEmail}}\",\r\n    \"mobilenumber\": \"{{$randomPhoneNumber}}\",\r\n    \"aadhar_number\": \"123\",\r\n    \"primary_location\": \"123\",\r\n    \"sibling\": \"N/A\",\r\n    \"twin\": \"No\",\r\n    \"fathername\": \"N/A\",\r\n    \"mothername\": \"N/A\",\r\n    \"emergencynumber\": \"2021071042\",\r\n    \"address\": {\r\n        \"country\": \"{{$randomCountry}}\",\r\n        \"state\": \"{{$randomStreetName}}\",\r\n        \"city\": \"{{$randomCity}}\",\r\n        \"landmark\": \"{{$randomStreetAddress}}\"\r\n    }\r\n}",
							"options": {
								"raw": {
									"language": "json"
								}
							}
						},
						"url": "http://localhost:3000/api/v1/healthcare/createpatientbiodata"
					},
					"status": "Created",
					"code": 201,
					"_postman_previewlanguage": "json",
					"header": [
						{
							"key": "Content-Type",
							"value": "application/json"
						},
						{
							"key": "Date",
							"value": "Sat, 26 Oct 2024 14:42:13 GMT"
						},
						{
							"key": "Content-Length",
							"value": "151"
						}
					],
					"cookie": [],
					"body": "{\n    \"Full name\": \"Dale Haley Kumar Wolff\",\n    \"message\": \"data has been successfully created!\",\n    \"patient_healthID\": \"HIDdf33751b-c7f5-4daf-a\",\n    \"status\": \"created\"\n}"
				}
			]
		},
		{
			"name": "Get Patient Bio Data",
			"request": {
				"auth": {
					"type": "bearer",
					"bearer": {
						"token": "{{HIP_TOKEN}}"
					}
				},
				"method": "GET",
				"header": [],
				"url": {
					"raw": "http://localhost/api/v1/healthcare/getpatientbiodata?healthID={{health_id}}",
					"protocol": "http",
					"host": [
						"localhost"
					],
					"path": [
						"api",
						"v1",
						"healthcare",
						"getpatientbiodata"
					],
					"query": [
						{
							"key": "healthID",
							"value": "{{health_id}}"
						}
					]
				}
			},
			"response": [
				{
					"name": "Get Patient Bio Data",
					"originalRequest": {
						"method": "GET",
						"header": [],
						"url": {
							"raw": "http://localhost:3000/api/v1/healthcare/getpatientbiodata?healthID={{healthID}}",
							"protocol": "http",
							"host": [
								"localhost"
							],
							"port": "3000",
							"path": [
								"api",
								"v1",
								"healthcare",
								"getpatientbiodata"
							],
							"query": [
								{
									"key": "healthID",
									"value": "{{healthID}}"
								}
							]
						}
					},
					"status": "OK",
					"code": 200,
					"_postman_previewlanguage": "json",
					"header": [
						{
							"key": "Content-Type",
							"value": "application/json"
						},
						{
							"key": "Date",
							"value": "Sat, 26 Oct 2024 14:42:20 GMT"
						},
						{
							"key": "Content-Length",
							"value": "630"
						}
					],
					"cookie": [],
					"body": "{\n    \"health_id\": \"HIDdf33751b-c7f5-4daf-a\",\n    \"fname\": \"Dale Haley\",\n    \"middlename\": \"Kumar\",\n    \"lname\": \"Wolff\",\n    \"sex\": \"Male\",\n    \"healthcare_id\": \"HCID04bd4df0-060d-43d1-a\",\n    \"dob\": \"DOMD\",\n    \"bloodgrp\": \"N/A\",\n    \"bmi\": \"N/A\",\n    \"marriage_status\": \"Single\",\n    \"weight\": \"N/A\",\n    \"email\": \"Macie.Lesch@gmail.com\",\n    \"mobilenumber\": \"206-500-0372\",\n    \"aadhar_number\": \"123\",\n    \"primary_location\": \"123\",\n    \"sibling\": \"N/A\",\n    \"twin\": \"No\",\n    \"fathername\": \"N/A\",\n    \"mothername\": \"N/A\",\n    \"emergencynumber\": \"2021071042\",\n    \"created_at\": \"2024-10-26T14:42:13.726Z\",\n    \"updated_at\": \"2024-10-26T14:42:13.726Z\",\n    \"address\": {\n        \"country\": \"Israel\",\n        \"state\": \"Abel Fords\",\n        \"city\": \"New Michele\",\n        \"landmark\": \"94939 Emmy Mountain\"\n    }\n}"
				}
			]
		},
		{
			"name": "Get Healthcare details",
			"request": {
				"auth": {
					"type": "bearer",
					"bearer": {
						"token": "{{HIP_TOKEN}}"
					}
				},
				"method": "GET",
				"header": [],
				"url": {
					"raw": "http://localhost/api/v1/healthcare/details?cache=true",
					"protocol": "http",
					"host": [
						"localhost"
					],
					"path": [
						"api",
						"v1",
						"healthcare",
						"details"
					],
					"query": [
						{
							"key": "cache",
							"value": "true"
						}
					]
				}
			},
			"response": [
				{
					"name": "Get Healthcare details (without cache)",
					"originalRequest": {
						"method": "GET",
						"header": [],
						"url": {
							"raw": "http://localhost:3000/api/v1/healthcare/details?cache=false",
							"protocol": "http",
							"host": [
								"localhost"
							],
							"port": "3000",
							"path": [
								"api",
								"v1",
								"healthcare",
								"details"
							],
							"query": [
								{
									"key": "cache",
									"value": "false"
								}
							]
						}
					},
					"status": "OK",
					"code": 200,
					"_postman_previewlanguage": "json",
					"header": [
						{
							"key": "Content-Type",
							"value": "application/json"
						},
						{
							"key": "Date",
							"value": "Sat, 26 Oct 2024 05:43:06 GMT"
						},
						{
							"key": "Content-Length",
							"value": "528"
						}
					],
					"cookie": [],
					"body": "{\n    \"healthcare\": {\n        \"healthcare_id\": \"HCID4ccc818e-bfcc-459d-a\",\n        \"healthcare_license\": \"4ccc818e-bfcc-459d-a\",\n        \"name\": \"Conrad Lesch Hospital\",\n        \"email\": \"Gaylord79@gmail.com\",\n        \"availability\": \"Yes\",\n        \"total_facilities\": 200,\n        \"total_mbbs_doc\": 58,\n        \"total_worker\": 400,\n        \"no_of_beds\": 200,\n        \"about\": \"Dynamic\",\n        \"date_of_registration\": \"0001-01-01T00:00:00Z\",\n        \"password\": \"$2a$10$6q.TnX1OhPOM/Xspk4RCcetUjcyY4zluZA.CDcuEMmnBKW/okpkTq\",\n        \"address\": {\n            \"country\": \"Myanmar\",\n            \"state\": \"Lake Orionburgh\",\n            \"city\": \"Elroyville\",\n            \"landmark\": \"Towne Lodge\"\n        }\n    }\n}"
				},
				{
					"name": "Get Healthcare details (with cache)",
					"originalRequest": {
						"method": "GET",
						"header": [],
						"url": {
							"raw": "http://localhost:3000/api/v1/healthcare/details?cache=true",
							"protocol": "http",
							"host": [
								"localhost"
							],
							"port": "3000",
							"path": [
								"api",
								"v1",
								"healthcare",
								"details"
							],
							"query": [
								{
									"key": "cache",
									"value": "true"
								}
							]
						}
					},
					"status": "OK",
					"code": 200,
					"_postman_previewlanguage": "json",
					"header": [
						{
							"key": "Content-Type",
							"value": "application/json"
						},
						{
							"key": "Date",
							"value": "Sat, 26 Oct 2024 05:47:30 GMT"
						},
						{
							"key": "Content-Length",
							"value": "506"
						}
					],
					"cookie": [],
					"body": "{\n    \"preferance\": {\n        \"healthcare_id\": \"HCID4ccc818e-bfcc-459d-a\",\n        \"healthcare_license\": \"4ccc818e-bfcc-459d-a\",\n        \"name\": \"Conrad Lesch Hospital\",\n        \"email\": \"Gaylord79@gmail.com\",\n        \"availability\": \"Yes\",\n        \"total_facilities\": 200,\n        \"total_mbbs_doc\": 58,\n        \"total_worker\": 400,\n        \"no_of_beds\": 200,\n        \"about\": \"Dynamic\",\n        \"date_of_registration\": \"0001-01-01T00:00:00Z\",\n        \"password\": \"$2a$10$6q.TnX1OhPOM/Xspk4RCcetUjcyY4zluZA.CDcuEMmnBKW/okpkTq\",\n        \"address\": {\n            \"country\": \"Myanmar\",\n            \"state\": \"Lake Orionburgh\",\n            \"city\": \"Elroyville\",\n            \"landmark\": \"Towne Lodge\"\n        }\n    }\n}"
				}
			]
		},
		{
			"name": "Create Records",
			"request": {
				"auth": {
					"type": "bearer",
					"bearer": {
						"token": "{{HIP_TOKEN}}"
					}
				},
				"method": "POST",
				"header": [],
				"body": {
					"mode": "raw",
					"raw": "{\r\n    \"issue\":\"{{$randomCatchPhraseNoun}}\",\r\n    \"description\":\"{{$randomJobDescriptor}}\",\r\n    \"health_id\":\"{{health_id}}\",\r\n    \"medical_severity\":\"High\"\r\n}",
					"options": {
						"raw": {
							"language": "json"
						}
					}
				},
				"url": "http://localhost/api/v1/healthcare/createrecords"
			},
			"response": [
				{
					"name": "Create Records",
					"originalRequest": {
						"method": "POST",
						"header": [],
						"body": {
							"mode": "raw",
							"raw": "{\r\n    \"issue\":\"Golang issue\",\r\n    \"description\":\"Golang description\",\r\n    \"health_id\":\"2021071042\",\r\n    \"medical_severity\":\"golang medical medical_severity\"\r\n}",
							"options": {
								"raw": {
									"language": "json"
								}
							}
						},
						"url": "http://localhost:3000/api/v1/healthcare/createrecords"
					},
					"status": "Created",
					"code": 201,
					"_postman_previewlanguage": "json",
					"header": [
						{
							"key": "Content-Type",
							"value": "application/json"
						},
						{
							"key": "Date",
							"value": "Sat, 26 Oct 2024 14:42:27 GMT"
						},
						{
							"key": "Content-Length",
							"value": "55"
						}
					],
					"cookie": [],
					"body": "{\n    \"message\": \"successfully Created\",\n    \"status\": \"pending \"\n}"
				}
			]
		},
		{
			"name": "Get Patient Records",
			"request": {
				"auth": {
					"type": "bearer",
					"bearer": {
						"token": "{{HIP_TOKEN}}"
					}
				},
				"method": "GET",
				"header": [],
				"url": {
					"raw": "http://localhost/api/v1/healthcare/getpatientrecords?healthID={{health_id}}&list=5&severity=High",
					"protocol": "http",
					"host": [
						"localhost"
					],
					"path": [
						"api",
						"v1",
						"healthcare",
						"getpatientrecords"
					],
					"query": [
						{
							"key": "healthID",
							"value": "{{health_id}}"
						},
						{
							"key": "list",
							"value": "5"
						},
						{
							"key": "severity",
							"value": "High"
						}
					]
				}
			},
			"response": [
				{
					"name": "Get Patient Records",
					"originalRequest": {
						"method": "GET",
						"header": [],
						"url": {
							"raw": "http://localhost:3000/api/v1/healthcare/getpatientrecords?healthID={{healthID}}&list=2",
							"protocol": "http",
							"host": [
								"localhost"
							],
							"port": "3000",
							"path": [
								"api",
								"v1",
								"healthcare",
								"getpatientrecords"
							],
							"query": [
								{
									"key": "healthID",
									"value": "{{healthID}}"
								},
								{
									"key": "list",
									"value": "2"
								}
							]
						}
					},
					"status": "OK",
					"code": 200,
					"_postman_previewlanguage": "json",
					"header": [
						{
							"key": "Content-Type",
							"value": "application/json"
						},
						{
							"key": "Date",
							"value": "Sat, 26 Oct 2024 14:42:34 GMT"
						},
						{
							"key": "Content-Length",
							"value": "64"
						}
					],
					"cookie": [],
					"body": "{\n    \"message\": \"successfull\",\n    \"pagination\": 2,\n    \"patient_records\": null\n}"
				}
			]
		},
		{
			"name": "Update Patient Data",
			"request": {
				"auth": {
					"type": "bearer",
					"bearer": {
						"token": "{{HIP_TOKEN}}"
					}
				},
				"method": "PATCH",
				"header": [],
				"body": {
					"mode": "raw",
					"raw": "{\r\n    \"fname\": \"{{$randomFirstName}}\",\r\n    \"dob\": \"{{$randomDatePast}}\",\r\n    \"bmi\": \"{{$randomPhoneNumberExt}}\"\r\n}",
					"options": {
						"raw": {
							"language": "json"
						}
					}
				},
				"url": {
					"raw": "http://localhost/api/v1/healthcare/updatepatientbiodata?healthID={{health_id}}",
					"protocol": "http",
					"host": [
						"localhost"
					],
					"path": [
						"api",
						"v1",
						"healthcare",
						"updatepatientbiodata"
					],
					"query": [
						{
							"key": "healthID",
							"value": "{{health_id}}"
						}
					]
				}
			},
			"response": [
				{
					"name": "Update Patient Data",
					"originalRequest": {
						"method": "PATCH",
						"header": [],
						"body": {
							"mode": "raw",
							"raw": "{\r\n    \"fname\": \"Helen of Troy\",\r\n    \"dob\": \"20/09/2001\",\r\n    \"bmi\": \"13\"\r\n}",
							"options": {
								"raw": {
									"language": "json"
								}
							}
						},
						"url": {
							"raw": "http://localhost:3000/api/v1/healthcare/updatepatientbiodata?healthID={{healthID}}",
							"protocol": "http",
							"host": [
								"localhost"
							],
							"port": "3000",
							"path": [
								"api",
								"v1",
								"healthcare",
								"updatepatientbiodata"
							],
							"query": [
								{
									"key": "healthID",
									"value": "{{healthID}}"
								}
							]
						}
					},
					"status": "Accepted",
					"code": 202,
					"_postman_previewlanguage": "json",
					"header": [
						{
							"key": "Content-Type",
							"value": "application/json"
						},
						{
							"key": "Date",
							"value": "Sat, 26 Oct 2024 14:42:44 GMT"
						},
						{
							"key": "Content-Length",
							"value": "658"
						}
					],
					"cookie": [],
					"body": "{\n    \"updated_details\": {\n        \"health_id\": \"HIDdf33751b-c7f5-4daf-a\",\n        \"fname\": \"Helen of Troy\",\n        \"middlename\": \"Kumar\",\n        \"lname\": \"Wolff\",\n        \"sex\": \"Male\",\n        \"healthcare_id\": \"HCID04bd4df0-060d-43d1-a\",\n        \"dob\": \"20/09/2001\",\n        \"bloodgrp\": \"N/A\",\n        \"bmi\": \"13\",\n        \"marriage_status\": \"Single\",\n        \"weight\": \"N/A\",\n        \"email\": \"Macie.Lesch@gmail.com\",\n        \"mobilenumber\": \"206-500-0372\",\n        \"aadhar_number\": \"123\",\n        \"primary_location\": \"123\",\n        \"sibling\": \"N/A\",\n        \"twin\": \"No\",\n        \"fathername\": \"N/A\",\n        \"mothername\": \"N/A\",\n        \"emergencynumber\": \"2021071042\",\n        \"created_at\": \"2024-10-26T14:42:13.726Z\",\n        \"updated_at\": \"2024-10-26T14:42:44.799Z\",\n        \"address\": {\n            \"country\": \"Israel\",\n            \"state\": \"Abel Fords\",\n            \"city\": \"New Michele\",\n            \"landmark\": \"94939 Emmy Mountain\"\n        }\n    }\n}"
				}
			]
		},
		{
			"name": "Assign Appointment",
			"request": {
				"auth": {
					"type": "bearer",
					"bearer": {
						"token": "{{HIP_TOKEN}}"
					}
				},
				"method": "POST",
				"header": [],
				"body": {
					"mode": "raw",
					"raw": "{\r\n    \"id\": \"{{app_id}}\",\r\n    \"health_id\": \"{{health_id}}\",\r\n    \"status\": \"Confirmed\"\r\n}",
					"options": {
						"raw": {
							"language": "json"
						}
					}
				},
				"url": {
					"raw": "http://localhost/api/v1/healthcare/appointments/set?list=10",
					"protocol": "http",
					"host": [
						"localhost"
					],
					"path": [
						"api",
						"v1",
						"healthcare",
						"appointments",
						"set"
					],
					"query": [
						{
							"key": "list",
							"value": "10"
						}
					]
				}
			},
			"response": [
				{
					"name": "Assign Appointment [ ERROR ]",
					"originalRequest": {
						"method": "POST",
						"header": [],
						"body": {
							"mode": "raw",
							"raw": "{\r\n    \"id\": \"672b4738b96a9b8f83fadd57\",\r\n    \"health_id\": \"{{health_id}}a\",\r\n    \"status\": \"Confirmed\"\r\n}",
							"options": {
								"raw": {
									"language": "json"
								}
							}
						},
						"url": {
							"raw": "http://localhost/api/v1/healthcare/appointments/set?list=10",
							"protocol": "http",
							"host": [
								"localhost"
							],
							"path": [
								"api",
								"v1",
								"healthcare",
								"appointments",
								"set"
							],
							"query": [
								{
									"key": "list",
									"value": "10"
								}
							]
						}
					},
					"status": "Internal Server Error",
					"code": 500,
					"_postman_previewlanguage": "json",
					"header": [
						{
							"key": "Server",
							"value": "nginx/1.27.2"
						},
						{
							"key": "Date",
							"value": "Wed, 06 Nov 2024 10:46:51 GMT"
						},
						{
							"key": "Content-Type",
							"value": "application/json"
						},
						{
							"key": "Content-Length",
							"value": "80"
						},
						{
							"key": "Connection",
							"value": "keep-alive"
						}
					],
					"cookie": [],
					"body": "{\n    \"error\": \"no appointment found with id ObjectID(\\\"672b4738b96a9b8f83fadd57\\\")\"\n}"
				},
				{
					"name": "Assign Appointment",
					"originalRequest": {
						"method": "POST",
						"header": [],
						"body": {
							"mode": "raw",
							"raw": "{\r\n    \"id\": \"672b4738b96a9b8f83fadd57\",\r\n    \"health_id\": \"{{health_id}}\",\r\n    \"status\": \"Confirmed\"\r\n}",
							"options": {
								"raw": {
									"language": "json"
								}
							}
						},
						"url": {
							"raw": "http://localhost/api/v1/healthcare/appointments/set?list=10",
							"protocol": "http",
							"host": [
								"localhost"
							],
							"path": [
								"api",
								"v1",
								"healthcare",
								"appointments",
								"set"
							],
							"query": [
								{
									"key": "list",
									"value": "10"
								}
							]
						}
					},
					"status": "OK",
					"code": 200,
					"_postman_previewlanguage": "json",
					"header": [
						{
							"key": "Server",
							"value": "nginx/1.27.2"
						},
						{
							"key": "Date",
							"value": "Wed, 06 Nov 2024 10:47:10 GMT"
						},
						{
							"key": "Content-Type",
							"value": "application/json"
						},
						{
							"key": "Content-Length",
							"value": "308"
						},
						{
							"key": "Connection",
							"value": "keep-alive"
						}
					],
					"cookie": [],
					"body": "{\n    \"appointments\": {\n        \"id\": \"672b4738b96a9b8f83fadd57\",\n        \"appointment_date\": \"30-02-2025\",\n        \"appointment_time\": \"10:00 AM T0 12:00 PM\",\n        \"health_id\": \"HID4acfbd3e-8e7b-4f1a-9\",\n        \"department\": \"Dentist Deparment\",\n        \"note\": \"status testing goes here...\",\n        \"fullname\": \"Tom Russel Gusikowski\",\n        \"status\": \"Confirmed\"\n    },\n    \"status\": \"Updated\"\n}"
				}
			]
		}
	],
	"variable": [
		{
			"key": "HIP_TOKEN",
			"value": ""
		},
		{
			"key": "H_ID",
			"value": ""
		},
		{
			"key": "healthID",
			"value": ""
		},
		{
			"key": "app_id",
			"value": ""
		}
	]
}